avro_to_python/__init__.py
avro_to_python/cli.py
avro_to_python/classes/__init__.py
avro_to_python/classes/field.py
avro_to_python/classes/file.py
avro_to_python/classes/node.py
avro_to_python/classes/reference.py
avro_to_python/reader/__init__.py
avro_to_python/reader/read.py
avro_to_python/templates/baseTemplate.j2
avro_to_python/templates/fields/arrayField.j2
avro_to_python/templates/fields/fieldFactory.j2
avro_to_python/templates/fields/mapField.j2
avro_to_python/templates/fields/primitiveField.j2
avro_to_python/templates/fields/referenceField.j2
avro_to_python/templates/fields/unionField.j2
avro_to_python/templates/files/enum.j2
avro_to_python/templates/files/helpers.j2
avro_to_python/templates/files/init.j2
avro_to_python/templates/files/manifest.j2
avro_to_python/templates/files/pip_init.j2
avro_to_python/templates/files/record.j2
avro_to_python/templates/files/setup.j2
avro_to_python/templates/imports/basicImports.j2
avro_to_python/templates/imports/fileImports.j2
avro_to_python/templates/partials/avroSchema.j2
avro_to_python/templates/partials/footer.j2
avro_to_python/templates/partials/header.j2
avro_to_python/templates/partials/objectSetter.j2
avro_to_python/utils/__init__.py
avro_to_python/utils/exceptions.py
avro_to_python/utils/paths.py
avro_to_python/utils/avro/__init__.py
avro_to_python/utils/avro/helpers.py
avro_to_python/utils/avro/primitive_types.py
avro_to_python/utils/avro/files/__init__.py
avro_to_python/utils/avro/files/enum.py
avro_to_python/utils/avro/files/record.py
avro_to_python/utils/avro/types/__init__.py
avro_to_python/utils/avro/types/array.py
avro_to_python/utils/avro/types/enum.py
avro_to_python/utils/avro/types/map.py
avro_to_python/utils/avro/types/primitive.py
avro_to_python/utils/avro/types/record.py
avro_to_python/utils/avro/types/reference.py
avro_to_python/utils/avro/types/type_factory.py
avro_to_python/utils/avro/types/union.py
avro_to_python/writer/__init__.py
avro_to_python/writer/writer.py
lcdp_avro_to_python-0.3.3.post8.dist-info/AUTHORS.rst
lcdp_avro_to_python-0.3.3.post8.dist-info/LICENSE
lcdp_avro_to_python-0.3.3.post8.dist-info/METADATA
lcdp_avro_to_python-0.3.3.post8.dist-info/WHEEL
lcdp_avro_to_python-0.3.3.post8.dist-info/entry_points.txt
lcdp_avro_to_python-0.3.3.post8.dist-info/top_level.txt
lcdp_avro_to_python-0.3.3.post8.dist-info/RECORD
