Metadata-Version: 2.1
Name: lcdp_avro_to_python
Version: 0.3.3.post8
Summary: avro-to-python is a light tool for compiling avro schema files (.avsc) to python classes making using avro schemata easy.
Home-page: https://github.com/LeComptoirDesPharmacies/avro-to-python
Author: Scott Rothbarth
Author-email: srserves85@gmail.com
License: MIT license
Keywords: avro-to-python
Classifier: Development Status :: 2 - Pre-Alpha
Classifier: Intended Audience :: Developers
Classifier: License :: OSI Approved :: MIT License
Classifier: Natural Language :: English
Classifier: Programming Language :: Python :: 3
Classifier: Programming Language :: Python :: 3.5
Classifier: Programming Language :: Python :: 3.6
Classifier: Programming Language :: Python :: 3.7
Classifier: Programming Language :: Python :: 3.8
Requires-Python: >3.5, !=3.0.*, !=3.1.*, !=3.2.*, !=3.3.*, !=3.4.*
License-File: LICENSE
License-File: AUTHORS.rst
Requires-Dist: Jinja2 >=2.10.3
Requires-Dist: Click ==8.1.7
